LICENSE
MANIFEST.in
README.md
setup.cfg
setup.py
sanic_validation/__init__.py
sanic_validation/decorators.py
sanic_validation.egg-info/PKG-INFO
sanic_validation.egg-info/SOURCES.txt
sanic_validation.egg-info/dependency_links.txt
sanic_validation.egg-info/requires.txt
sanic_validation.egg-info/top_level.txt