Metadata-Version: 2.1
Name: sanic-validation
Version: 0.5.1
Summary: Validation for sanic endpoints
Home-page: https://github.com/piotrb5e3/sanic-validation
Author: Piotr Bakalarski
Author-email: piotrb5e3@gmail.com
License: GPLv3
Platform: UNKNOWN
Classifier: Development Status :: 4 - Beta
Classifier: Intended Audience :: Developers
Classifier: License :: OSI Approved :: GNU General Public License v3 (GPLv3)
Classifier: Environment :: Web Environment
Classifier: Programming Language :: Python :: 3.6
Classifier: Programming Language :: Python :: 3.7
Classifier: Programming Language :: Python :: 3.8
